COPYING
MANIFEST.in
README.md
requirements.txt
setup.py
doc/build/html/.buildinfo
doc/build/html/genindex.html
doc/build/html/index.html
doc/build/html/objects.inv
doc/build/html/search.html
doc/build/html/searchindex.js
doc/build/html/_sources/index.rst.txt
doc/build/html/_sources/user_guide/index.rst.txt
doc/build/html/_static/alabaster.css
doc/build/html/_static/basic.css
doc/build/html/_static/custom.css
doc/build/html/_static/doctools.js
doc/build/html/_static/documentation_options.js
doc/build/html/_static/file.png
doc/build/html/_static/jquery-3.5.1.js
doc/build/html/_static/jquery.js
doc/build/html/_static/language_data.js
doc/build/html/_static/minus.png
doc/build/html/_static/plus.png
doc/build/html/_static/pygments.css
doc/build/html/_static/searchtools.js
doc/build/html/_static/underscore-1.3.1.js
doc/build/html/_static/underscore.js
doc/build/html/user_guide/index.html
manipylator/__init__.py
manipylator/analysis.py
manipylator/controller.py
manipylator/gui.py
manipylator/signals.py
manipylator/utils.py
manipylator.egg-info/PKG-INFO
manipylator.egg-info/SOURCES.txt
manipylator.egg-info/dependency_links.txt
manipylator.egg-info/entry_points.txt
manipylator.egg-info/requires.txt
manipylator.egg-info/top_level.txt
test_package/__init__.py