Metadata-Version: 2.1
Name: manipylator
Version: 0.1rc0
Summary: a Python-driven manipulator controller
Home-page: https://gitlab.pasteur.fr/amichaut/manipylator/
Author: Arthur Michaut
Author-email: arthur.michaut@gmail.com
License: GPLv3
Platform: UNKNOWN
Classifier: Development Status :: 5 - Production/Stable
Classifier: Environment :: Console
Classifier: Operating System :: POSIX
Classifier: Operating System :: Microsoft :: Windows
Classifier: Programming Language :: Python :: 3
Classifier: Programming Language :: Python :: 3.6
Classifier: Programming Language :: Python :: 3.7
Classifier: Programming Language :: Python :: 3.8
Classifier: Intended Audience :: Science/Research
Classifier: Topic :: Scientific/Engineering :: Bio-Informatics
Requires-Python: >=3.6
License-File: COPYING
